stt_uk/asr.py
stt_uk/version.txt
stt_uk-0.1.0.dist-info/METADATA
stt_uk-0.1.0.dist-info/WHEEL
stt_uk-0.1.0.dist-info/RECORD
